LICENSE
MANIFEST.in
README.rst
requirements.txt
setup.py
anymarkup_core/__init__.py
anymarkup_core.egg-info/PKG-INFO
anymarkup_core.egg-info/SOURCES.txt
anymarkup_core.egg-info/dependency_links.txt
anymarkup_core.egg-info/requires.txt
anymarkup_core.egg-info/top_level.txt
test/__init__.py
test/test_libs_not_installed.py
test/test_parse.py
test/test_serialize.py
test/fixtures/bad_extension.xml
test/fixtures/empty.ini
test/fixtures/empty.json
test/fixtures/empty.json5
test/fixtures/empty.toml
test/fixtures/empty.xml
test/fixtures/empty.yaml
test/fixtures/example.ini
test/fixtures/example.json
test/fixtures/example.json5
test/fixtures/example.toml
test/fixtures/example.xml
test/fixtures/example.yaml
test/fixtures/example_omap.yaml
test/fixtures/types.json
test/fixtures/without_extension