Metadata-Version: 1.1
Name: anymarkup-core
Version: 0.7.0
Summary: Core library for anymarkup
Home-page: https://github.com/bkabrda/anymarkup-core
Author: Slavek Kabrda
Author-email: slavek.kabrda@gmail.com
License: BSD
Keywords: xml,yaml,toml,json,json5,ini
Platform: UNKNOWN
Classifier: Development Status :: 4 - Beta
Classifier: Intended Audience :: Developers
Classifier: License :: OSI Approved :: BSD License
Classifier: Operating System :: POSIX :: Linux
Classifier: Programming Language :: Python
Classifier: Programming Language :: Python :: 2.7
Classifier: Programming Language :: Python :: 3.3
Classifier: Programming Language :: Python :: 3.4
Classifier: Programming Language :: Python :: 3.5
